{"name":"t:sections.header.name","type":"header","sections":{"announcement-bar":{"type":"announcement-bar","blocks":{"announcement-bar-0":{"type":"announcement","settings":{"text":"Welcome to our store","link":""}}},"block_order":["announcement-bar-0"],"settings":{"color_scheme":"background-1","show_line_separator":true,"show_social":true,"auto_rotate":false,"change_slides_speed":5,"enable_country_selector":true,"enable_language_selector":false}},"3456a9d8-6a4b-43af-bcdd-c5dc251d46a5":{"type":"announcement-bar","disabled":true,"blocks":{"sections--16141998653614__3456a9d8-6a4b-43af-bcdd-c5dc251d46a5-announcement-1":{"type":"announcement","settings":{"text":"Welcome to our store","link":""}}},"block_order":["sections--16141998653614__3456a9d8-6a4b-43af-bcdd-c5dc251d46a5-announcement-1"],"settings":{"color_scheme":"","show_line_separator":true,"show_social":false,"auto_rotate":false,"change_slides_speed":5,"enable_country_selector":false,"enable_language_selector":false}},"5877ee65-9de6-4242-8568-0df0647dd232":{"type":"announcement-bar","disabled":true,"blocks":{"sections--16141998653614__5877ee65-9de6-4242-8568-0df0647dd232-announcement-1":{"type":"announcement","settings":{"text":"Welcome to our store","link":""}}},"block_order":["sections--16141998653614__5877ee65-9de6-4242-8568-0df0647dd232-announcement-1"],"settings":{"color_scheme":"","show_line_separator":true,"show_social":false,"auto_rotate":false,"change_slides_speed":5,"enable_country_selector":false,"enable_language_selector":false}},"10970a3f-0e8f-474d-b2af-10fb61f69e0c":{"type":"announcement-bar","disabled":true,"blocks":{"sections--16141998653614__10970a3f-0e8f-474d-b2af-10fb61f69e0c-announcement-1":{"type":"announcement","settings":{"text":"Welcome to our store","link":""}}},"block_order":["sections--16141998653614__10970a3f-0e8f-474d-b2af-10fb61f69e0c-announcement-1"],"settings":{"color_scheme":"","show_line_separator":true,"show_social":false,"auto_rotate":false,"change_slides_speed":5,"enable_country_selector":false,"enable_language_selector":false}},"header":{"type":"header","settings":{"logo_position":"middle-left","menu":"main-menu","menu_type_desktop":"dropdown","sticky_header_type":"on-scroll-up","show_line_separator":true,"color_scheme":"background-1","menu_color_scheme":"background-1","enable_country_selector":true,"enable_language_selector":true,"mobile_logo_position":"center","margin_bottom":0,"padding_top":20,"padding_bottom":20}}},"order":["announcement-bar","3456a9d8-6a4b-43af-bcdd-c5dc251d46a5","5877ee65-9de6-4242-8568-0df0647dd232","10970a3f-0e8f-474d-b2af-10fb61f69e0c","header"]}